diagralhomekit/__init__.py
diagralhomekit/__main__.py
diagralhomekit/alarm_system.py
diagralhomekit/config.py
diagralhomekit/diagral.py
diagralhomekit/homekit_alarm.py
diagralhomekit/http_plugin.py
diagralhomekit/main.py
diagralhomekit/meteofrance.py
diagralhomekit/nut.py
diagralhomekit/plex.py
diagralhomekit/plugin.py
diagralhomekit/utils.py
diagralhomekit-0.9.16.dist-info/LICENSE
diagralhomekit-0.9.16.dist-info/METADATA
diagralhomekit-0.9.16.dist-info/WHEEL
diagralhomekit-0.9.16.dist-info/entry_points.txt
diagralhomekit-0.9.16.dist-info/RECORD
