Metadata-Version: 2.3
Name: diagralhomekit
Version: 0.9.16
Summary: Apple HomeKit integration for Diagral alarm systems
License: CECILL-B
Author: d9pouces
Author-email: github@19pouces.net
Requires-Python: >=3.9,<4.0
Classifier: Development Status :: 5 - Production/Stable
Classifier: License :: CeCILL-B Free Software License Agreement (CECILL-B)
Classifier: License :: OSI Approved :: CEA CNRS Inria Logiciel Libre License, version 2.1 (CeCILL-2.1)
Classifier: Natural Language :: English
Classifier: Natural Language :: French
Classifier: Operating System :: MacOS :: MacOS X
Classifier: Operating System :: POSIX :: BSD
Classifier: Operating System :: POSIX :: Linux
Classifier: Operating System :: Unix
Classifier: Programming Language :: Python :: 3
Classifier: Programming Language :: Python :: 3.9
Classifier: Programming Language :: Python :: 3.10
Classifier: Programming Language :: Python :: 3.11
Classifier: Programming Language :: Python :: 3.12
Classifier: Programming Language :: Python :: 3.13
Classifier: Programming Language :: Python :: 3 :: Only
Requires-Dist: HAP-python (>=4.6.0,<5.0.0)
Requires-Dist: base36 (>=0.1.1,<0.2.0)
Requires-Dist: meteofrance-api (>=1.2.0,<2.0.0)
Requires-Dist: nut2 (>=2.1.1,<3.0.0)
Requires-Dist: pyqrcode (>=1.2.1,<2.0.0)
Requires-Dist: requests (>=2.28.2,<3.0.0)
Requires-Dist: systemlogger (>=0.2.2,<0.3.0)
